[
    {
      "id": 1,
      "iframeSrc": "https://www.linkedin.com/embed/feed/update/urn:li:share:7290815477830844416"
    },
    {
      "id": 2,
      "iframeSrc": "https://www.linkedin.com/embed/feed/update/urn:li:share:7290815478791311360"
    },
    {
      "id": 3,
      "iframeSrc": "https://www.linkedin.com/embed/feed/update/urn:li:share:7290815478905878528"
    },
    {
      "id": 4,
      "iframeSrc": "https://www.linkedin.com/embed/feed/update/urn:li:share:7290815479000000000"
    }
  ]
  